ninja_extra/__init__.py
ninja_extra/apps.py
ninja_extra/compatible.py
ninja_extra/constants.py
ninja_extra/context.py
ninja_extra/dependency_resolver.py
ninja_extra/details.py
ninja_extra/exceptions.py
ninja_extra/generic.py
ninja_extra/helper.py
ninja_extra/lazy.py
ninja_extra/logger.py
ninja_extra/main.py
ninja_extra/modules.py
ninja_extra/operation.py
ninja_extra/py.typed
ninja_extra/router.py
ninja_extra/shortcuts.py
ninja_extra/signals.py
ninja_extra/status.py
ninja_extra/types.py
ninja_extra/urls.py
ninja_extra/conf/__init__.py
ninja_extra/conf/decorator.py
ninja_extra/conf/package_settings.py
ninja_extra/controllers/__init__.py
ninja_extra/controllers/base.py
ninja_extra/controllers/registry.py
ninja_extra/controllers/utils.py
ninja_extra/controllers/model/__init__.py
ninja_extra/controllers/model/builder.py
ninja_extra/controllers/model/endpoints.py
ninja_extra/controllers/model/interfaces.py
ninja_extra/controllers/model/path_resolver.py
ninja_extra/controllers/model/schemas.py
ninja_extra/controllers/model/service.py
ninja_extra/controllers/route/__init__.py
ninja_extra/controllers/route/route_functions.py
ninja_extra/interfaces/ordering.py
ninja_extra/interfaces/route_context.py
ninja_extra/interfaces/searching.py
ninja_extra/ordering/__init__.py
ninja_extra/ordering/decorator.py
ninja_extra/ordering/models.py
ninja_extra/ordering/operation.py
ninja_extra/pagination/__init__.py
ninja_extra/pagination/decorator.py
ninja_extra/pagination/operations.py
ninja_extra/pagination/models/__init__.py
ninja_extra/pagination/models/page_by_number.py
ninja_extra/permissions/__init__.py
ninja_extra/permissions/base.py
ninja_extra/permissions/common.py
ninja_extra/reflect/__init__.py
ninja_extra/reflect/_reflect.py
ninja_extra/reflect/utils.py
ninja_extra/schemas/__init__.py
ninja_extra/schemas/response.py
ninja_extra/searching/__init__.py
ninja_extra/searching/decorators.py
ninja_extra/searching/models.py
ninja_extra/searching/operations.py
django_ninja_extra-0.31.0.dist-info/licenses/LICENSE
django_ninja_extra-0.31.0.dist-info/WHEEL
django_ninja_extra-0.31.0.dist-info/METADATA
django_ninja_extra-0.31.0.dist-info/RECORD
