Metadata-Version: 2.4
Name: django-ninja-extra
Version: 0.31.0
Summary: Django Ninja Extra - Class Based Utility and more for Django Ninja(Fast Django REST framework)
Home-page: https://github.com/eadwinCode/django-ninja-extra
Author: Ezeudoh Tochukwu
Author-email: tochukwu.ezeudoh@gmail.com
Requires-Python: >=3.7
Classifier: Development Status :: 5 - Production/Stable
Classifier: Intended Audience :: Information Technology
Classifier: Intended Audience :: System Administrators
Classifier: Operating System :: OS Independent
Classifier: Topic :: Internet
Classifier: Topic :: Software Development :: Libraries :: Application Frameworks
Classifier: Topic :: Software Development :: Libraries :: Python Modules
Classifier: Topic :: Software Development :: Libraries
Classifier: Topic :: Software Development
Classifier: Typing :: Typed
Classifier: Environment :: Web Environment
Classifier: Intended Audience :: Developers
Classifier: License :: OSI Approved :: MIT License
Classifier: Programming Language :: Python :: 3
Classifier: Programming Language :: Python :: 3.8
Classifier: Programming Language :: Python :: 3.9
Classifier: Programming Language :: Python :: 3.10
Classifier: Programming Language :: Python :: 3.11
Classifier: Programming Language :: Python :: 3.12
Classifier: Programming Language :: Python :: 3 :: Only
Classifier: Framework :: Django
Classifier: Framework :: Django :: 3.1
Classifier: Framework :: Django :: 3.2
Classifier: Framework :: Django :: 4.1
Classifier: Framework :: Django :: 4.2
Classifier: Framework :: Django :: 5.0
Classifier: Framework :: AsyncIO
Classifier: Topic :: Internet :: WWW/HTTP :: HTTP Servers
Classifier: Topic :: Internet :: WWW/HTTP
License-File: LICENSE
Requires-Dist: Django >= 2.2
Requires-Dist: django-ninja >= 1.5.3
Requires-Dist: injector >= 0.19.0
Requires-Dist: asgiref
Requires-Dist: contextlib2
Project-URL: Documentation, https://eadwincode.github.io/django-ninja-extra/
